{
  "data": {
    "id": "20260429_r85snhg2q",
    "timestamp": "2026-04-29 03:31:23",
    "date": "2026-04-29",
    "title": "历史镌刻于石上",
    "copyright": "塔霍河岸边的贝伦塔, 里斯本, 葡萄牙 (© f9photos/Getty Images)",
    "copyrightlink": "https://www.bing.com/search?q=%E8%B4%9D%E4%BC%A6%E5%A1%94&form=hpcapt&mkt=zh-cn",
    "urlbase": "/th?id=OHR.BelemTowerBank_ZH-CN6235906597",
    "url": "https://www.bing.com/th?id=OHR.BelemTowerBank_ZH-CN6235906597_1920x1080.jpg",
    "startdate": "20260428",
    "enddate": "20260429",
    "fullstartdate": "202604281600",
    "hsh": "9064fde134056043c4a22d6daab05dd8",
    "localPath": "/wallpapers/2026-04-29________.jpg"
  },
  "status": "success"
}