{
  "data": {
    "id": "20260314_cowv1ym50",
    "timestamp": "2026-03-14 02:24:36",
    "date": "2026-03-14",
    "title": "圆周率的古老启示",
    "copyright": "兰扬石门，位于英格兰康沃尔郡的一座兰扬新石器时代石棚墓，英国 (© Helen Hotson/Alamy)",
    "copyrightlink": "https://www.bing.com/search?q=%E5%9C%86%E5%91%A8%E7%8E%87%E6%97%A5&form=hpcapt&mkt=zh-cn",
    "urlbase": "/th?id=OHR.CornwallDolmen_ZH-CN0045468799",
    "url": "https://www.bing.com/th?id=OHR.CornwallDolmen_ZH-CN0045468799_1920x1080.jpg",
    "startdate": "20260313",
    "enddate": "20260314",
    "fullstartdate": "202603131600",
    "hsh": "37c5afc54db3dfb8b84b67261908baa1",
    "localPath": "/wallpapers/2026-03-14_________.jpg"
  },
  "status": "success"
}