{
  "id": "20260329_s19z4c454",
  "timestamp": "2026-03-29 02:46:32",
  "date": "2026-03-29",
  "title": "海边的宁静",
  "copyright": "佩吉角灯塔, 大西洋海岸, 新斯科舍省, 加拿大 (© Prashanth Bala/Shutterstock)",
  "copyrightlink": "https://www.bing.com/search?q=%E4%BD%A9%E5%90%89%E8%A7%92%E7%81%AF%E5%A1%94&form=hpcapt&mkt=zh-cn",
  "urlbase": "/th?id=OHR.PeggysLighthouse_ZH-CN5730463973",
  "url": "https://www.bing.com/th?id=OHR.PeggysLighthouse_ZH-CN5730463973_1920x1080.jpg",
  "startdate": "20260328",
  "enddate": "20260329",
  "fullstartdate": "202603281600",
  "hsh": "89174caee265ef8e63463a5630f6b58e",
  "localPath": "/wallpapers/2026-03-29______.jpg"
}